aerocast/__init__.py
aerocast/__main__.py
aerocast/airport.py
aerocast/api.py
aerocast/converter.py
aerocast/core.py
aerocast/tts_manager.py
aerocast/weather.py
AeroCast-0.1.6.dist-info/LICENSE
AeroCast-0.1.6.dist-info/METADATA
AeroCast-0.1.6.dist-info/WHEEL
AeroCast-0.1.6.dist-info/entry_points.txt
AeroCast-0.1.6.dist-info/top_level.txt
AeroCast-0.1.6.dist-info/RECORD
