Metadata-Version: 2.2
Name: AeroCast
Version: 0.1.6
Summary: A Python package for providing weather information for airports.
Home-page: https://github.com/Rbtsv2/AeroCast
Author: Charles FOURNIER
Author-email: charles.fournier@fih.digital
Keywords: weather,airport,METAR,TAF,aviation,forecast
Classifier: Development Status :: 3 - Alpha
Classifier: Intended Audience :: Developers
Classifier: License :: OSI Approved :: MIT License
Classifier: Programming Language :: Python :: 3
Classifier: Programming Language :: Python :: 3.7
Classifier: Natural Language :: English
Classifier: Operating System :: OS Independent
Classifier: Topic :: Software Development :: Libraries :: Python Modules
Classifier: Topic :: Scientific/Engineering :: Atmospheric Science
Requires-Python: >=3.7
License-File: LICENSE
Requires-Dist: requests
Requires-Dist: gtts
Requires-Dist: playsound3
Requires-Dist: Babel
Dynamic: author
Dynamic: author-email
Dynamic: classifier
Dynamic: description
Dynamic: description-content-type
Dynamic: home-page
Dynamic: keywords
Dynamic: requires-dist
Dynamic: requires-python
Dynamic: summary
